{
  "account_id": "supplements",
  "account_name": "Supplements Account",
  "handle": "Sadie \ud83e\udd89",
  "fetched_at": "2026-06-25T08:03:14.898517",
  "date_range": "last_30_days",
  "metrics": {
    "impressions": {
      "value": 261660.00000000003,
      "display": "261.66k",
      "change_pct": 568.0
    },
    "engagements": {
      "value": 11650.0,
      "display": "11.65k",
      "change_pct": 697.0
    },
    "outbound_clicks": {
      "value": 52.0,
      "display": "52",
      "change_pct": 919.0
    },
    "saves": {
      "value": 1680.0,
      "display": "1.68k",
      "change_pct": 390.0
    },
    "total_audience": {
      "value": 203640.0,
      "display": "203.64k",
      "change_pct": 564.0
    },
    "engaged_audience": {
      "value": 9680.0,
      "display": "9.68k",
      "change_pct": 728.0
    }
  },
  "top_pins": [
    {
      "title": "The #1 Supplement Everyone Needs\n; Opens a new tab",
      "impressions": "17,383",
      "url": "https://www.pinterest.com/pin/1143844005378172363/"
    },
    {
      "title": "Real Results With Vitamin D3 + K2\n; Opens a new tab",
      "impressions": "11,654",
      "url": "https://www.pinterest.com/pin/1143844005377909994/"
    },
    {
      "title": "I Tried Turmeric Curcumin for 60 Days\n; Opens a new tab",
      "impressions": "10,929",
      "url": "https://www.pinterest.com/pin/1143844005378107375/"
    },
    {
      "title": "My Secret to Stay Asleep\n; Opens a new tab",
      "impressions": "9,580",
      "url": "https://www.pinterest.com/pin/1143844005377718955/"
    },
    {
      "title": "Appetite Control Starts Here\n; Opens a new tab",
      "impressions": "9,072",
      "url": "https://www.pinterest.com/pin/1143844005377718968/"
    },
    {
      "title": "Melatonin Sleep Gummies Changed Everything\n; Opens a new tab",
      "impressions": "9,027",
      "url": "https://www.pinterest.com/pin/1143844005377696375/"
    },
    {
      "title": "Game Changer for Detox\n; Opens a new tab",
      "impressions": "8,211",
      "url": "https://www.pinterest.com/pin/1143844005377909025/"
    },
    {
      "title": "Stop Wasting Money on the Wrong Supplements\n; Opens a new tab",
      "impressions": "8,174",
      "url": "https://www.pinterest.com/pin/1143844005378172694/"
    },
    {
      "title": "Stop Wasting Money on the Wrong Supplements\n; Opens a new tab",
      "impressions": "7,336",
      "url": "https://www.pinterest.com/pin/1143844005378171585/"
    },
    {
      "title": "Best Supplement I've Ever Tried\n; Opens a new tab",
      "impressions": "6,722",
      "url": "https://www.pinterest.com/pin/1143844005378234189/"
    },
    {
      "title": "Vitamin D3 + K2: Worth the Hype?\n; Opens a new tab",
      "impressions": "6,184",
      "url": "https://www.pinterest.com/pin/1143844005378302510/"
    },
    {
      "title": "Joint Support Starts Here\n; Opens a new tab",
      "impressions": "6,149",
      "url": "https://www.pinterest.com/pin/1143844005378172773/"
    },
    {
      "title": "3 Supplements That Actually Work\n; Opens a new tab",
      "impressions": "6,111",
      "url": "https://www.pinterest.com/pin/1143844005377718035/"
    },
    {
      "title": "Alkalize Your Body Starts Here\n; Opens a new tab",
      "impressions": "5,415",
      "url": "https://www.pinterest.com/pin/1143844005378370810/"
    },
    {
      "title": "My Daily Wellness Staple\n; Opens a new tab",
      "impressions": "5,329",
      "url": "https://www.pinterest.com/pin/1143844005378171870/"
    }
  ],
  "raw_summary": "Impressions\n,\n261.66k\n,\n568%\nEngagements\n,\n11.65k\n,\n697%\nOutbound clicks\n,\n52\n,\n919%\nSaves\n,\n1.68k\n,\n390%\nTotal audience\n,\n203.64k\n,\n564%\nEngaged audience\n,\n9.68k\n,\n728%"
}